setup.py
pgmigrate/__init__.py
pgmigrate.egg-info/PKG-INFO
pgmigrate.egg-info/SOURCES.txt
pgmigrate.egg-info/dependency_links.txt
pgmigrate.egg-info/entry_points.txt
pgmigrate.egg-info/not-zip-safe
pgmigrate.egg-info/requires.txt
pgmigrate.egg-info/top_level.txt
pgmigrate/integrations/__init__.py
pgmigrate/integrations/django/__init__.py
pgmigrate/integrations/django/management/__init__.py
pgmigrate/integrations/django/management/commands/__init__.py
pgmigrate/integrations/django/management/commands/migrate.py