Metadata-Version: 1.0
Name: pgmigrate
Version: 1.2.1
Summary: Database schema migration tool for Postgres
Home-page: http://code.google.com/p/pgmigrate/
Author: Sergey Kirillov
Author-email: sergey.kirillov@gmail.com
License: Apache License 2.0
Keywords: database migration tool postgres
Platform: any
Classifier: Programming Language :: Python
Classifier: Operating System :: OS Independent
Classifier: Natural Language :: English
